[
    {
        "id":1,
        "name":"Story Book",
        "title":"Loerm,ipsum dolor sit amet consetetur adipicing edit",
        "price":0,
        "category":"Free",
        "image":"https://www.freepik.com/free-vector/hand-drawn-flat-design-stack-books-illustration_23974704.htm#fromView=search&page=1&position=2&uuid=a006244e-b965-4059-b0ed-b5ac434380b7"

    },
    {
        "id":2,
        "name":"Story Book",
        "title":"Loerm,ipsum dolor sit amet consetetur adipicing edit",
        "price":0,
        "category":"Free",
        "image":"https://www.freepik.com/free-vector/hand-drawn-flat-design-stack-books-illustration_23974704.htm#fromView=search&page=1&position=2&uuid=a006244e-b965-4059-b0ed-b5ac434380b7"

    },
    {
        "id":3,
        "name":"Music Book",
        "title":"Loerm,ipsum dolor sit amet consetetur adipicing edit",
        "price":100,
        "category":"Song",
        "image":"https://www.freepik.com/free-vector/hand-drawn-flat-design-stack-books-illustration_23974704.htm#fromView=search&page=1&position=2&uuid=a006244e-b965-4059-b0ed-b5ac434380b7"

    },
    {
        "id":4,
        "name":"Story Book",
        "title":"Loerm,ipsum dolor sit amet consetetur adipicing edit",
        "price":0,
        "category":"Free",
        "image":"https://www.freepik.com/free-vector/hand-drawn-flat-design-stack-books-illustration_23974704.htm#fromView=search&page=1&position=2&uuid=a006244e-b965-4059-b0ed-b5ac434380b7"

    },
    {
        "id":5,
        "name":"Food Book",
        "title":"Loerm,ipsum dolor sit amet consetetur adipicing edit",
        "price":80,
        "category":"Food",
        "image":"https://www.freepik.com/free-vector/hand-drawn-flat-design-stack-books-illustration_23974704.htm#fromView=search&page=1&position=2&uuid=a006244e-b965-4059-b0ed-b5ac434380b7"

    },
    {
        "id":6,
        "name":"Story Book",
        "title":"Loerm,ipsum dolor sit amet consetetur adipicing edit",
        "price":0,
        "category":"Free",
        "image":"https://www.freepik.com/free-vector/hand-drawn-flat-design-stack-books-illustration_23974704.htm#fromView=search&page=1&position=2&uuid=a006244e-b965-4059-b0ed-b5ac434380b7"

    },
    {
        "id":7,
        "name":"Story Book",
        "title":"Loerm,ipsum dolor sit amet consetetur adipicing edit",
        "price":0,
        "category":"Free",
        "image":"https://www.freepik.com/free-vector/hand-drawn-flat-design-stack-books-illustration_23974704.htm#fromView=search&page=1&position=2&uuid=a006244e-b965-4059-b0ed-b5ac434380b7"

    },
    {
        "id":8,
        "name":"Sports Book",
        "title":"Loerm,ipsum dolor sit amet consetetur adipicing edit",
        "price":100,
        "category":"Sports",
        "image":"https://www.freepik.com/free-vector/hand-drawn-flat-design-stack-books-illustration_23974704.htm#fromView=search&page=1&position=2&uuid=a006244e-b965-4059-b0ed-b5ac434380b7"

    }, 
    {
        "id":10,
        "name":"Comedy Book",
        "title":"Loerm,ipsum dolor sit amet consetetur adipicing edit",
        "price":50,
        "category":"Comedy",
        "image":"https://www.freepik.com/free-vector/hand-drawn-flat-design-stack-books-illustration_23974704.htm#fromView=search&page=1&position=2&uuid=a006244e-b965-4059-b0ed-b5ac434380b7"

    },
    {
        "id":11,
        "name":"Story Book",
        "title":"Loerm,ipsum dolor sit amet consetetur adipicing edit",
        "price":0,
        "category":"Free",
        "image":"https://www.freepik.com/free-vector/hand-drawn-flat-design-stack-books-illustration_23974704.htm#fromView=search&page=1&position=2&uuid=a006244e-b965-4059-b0ed-b5ac434380b7"

    }
]
